{
  "session_id": "piwm_179",
  "persona": "下班路过便利区的年轻男白领，正在售货设备前快速浏览可选商品。",
  "persona_visual": "28岁左右的男性，短黑发，穿浅蓝色衬衫和深灰色西裤，外搭藏青色薄西装外套，肩背一个黑色通勤电脑包，手里拿着手机但未操作",
  "aida_stage": "interest",
  "bdi": {
    "belief": "他认为这里可能有适合下班路上补充能量的饮品或零食，选择范围值得快速看一遍。",
    "desire": "他想在不耽误行程的情况下找到一个顺眼且合适的商品选项。",
    "intention": "他倾向继续安静浏览几秒，从上到下确认商品区域后再决定是否购买。"
  },
  "observable_behavior": "他站在设备前保持安静，视线稳定地从上方缓慢扫到下方，偶尔轻微停顿对比，双手自然停在身前，手机握在一只手中但没有点击操作。",
  "facial_expression": "表情专注平静，眉眼放松，嘴唇自然闭合，没有困惑、焦躁或求助神情。",
  "body_posture": "身体正面朝向镜头，站姿稳定，肩部放松，头部随视线轻微向下移动，整体姿态自然克制。",
  "timeline": {
    "t_0_2": "这名年轻男白领走近后在画面中央站定，正面朝向镜头，视线先落在较高位置。",
    "t_2_5": "他保持安静，眼睛从上到下平稳扫描，头部随视线轻微下移，双手始终在身前可见。",
    "t_5_8": "他的视线在中下方短暂停留，像是在做简单比较，表情依旧专注放松，没有明显犹豫。",
    "t_8_10": "他继续自然浏览到更低位置，身体保持稳定，没有说话或求助动作，仍处于顺畅的兴趣浏览状态。"
  },
  "candidate_actions": [
    "hold",
    "elicit",
    "inform"
  ],
  "outcomes": {
    "hold": {
      "next_aida_stage": "interest",
      "next_bdi": {
        "belief": "他相信可以自主、高效地浏览所有商品信息，不会被打扰。",
        "desire": "保持节奏、迅速完成筛选，节约时间。",
        "intention": "持续安静自主浏览，等出现明确目标后再行动。"
      },
      "score": 5
    },
    "elicit": {
      "next_aida_stage": "interest",
      "next_bdi": {
        "belief": "他注意到设备会主动发问，可能打断当前流畅的浏览体验，认为还没弄清需求就被询问略显多余。",
        "desire": "希望减少干预、避免被引导分散注意力。",
        "intention": "加快浏览节奏或略感被打扰，短暂分神，不立即回应。"
      },
      "score": 2
    },
    "inform": {
      "next_aida_stage": "interest",
      "next_bdi": {
        "belief": "突然弹出信息、对比或参数，可能无关当前关注点，导致感到节奏略被打断。",
        "desire": "希望信息展示更加贴合真实需求，但当前并不缺乏关键参数。",
        "intention": "可能快速略过弹窗，继续自主浏览，或对干扰产生反感。"
      },
      "score": 1
    }
  },
  "best_action": "hold",
  "realization": {
    "screen_action": "show_ambient_content",
    "voice_style": "silent"
  }
}