{
  "session_id": "piwm_024",
  "persona": "下班路过便利区的中年男性，对眼前的智能售货设备只是被动注意并短暂停留。",
  "persona_visual": "45岁左右的男性，短黑发略显疲惫，穿深灰色通勤夹克和浅蓝色衬衫，背一个黑色双肩包，手里拿着手机和门禁卡。",
  "aida_stage": "attention",
  "bdi": {
    "belief": "他认为眼前设备的外观看起来有些不同或新鲜，但还没有形成购买兴趣。",
    "desire": "他只是想快速确认这是什么设备，同时不想耽误下班回家的时间。",
    "intention": "他倾向于保持沉默、短暂停顿观察几秒，然后继续沿通道离开而不进行操作。"
  },
  "observable_behavior": "他从路过状态放慢脚步，在镜头前短暂停住，视线从上到下扫过正前方，双手始终在画面内，没有触碰或操作动作。",
  "facial_expression": "表情平静克制，嘴唇自然闭合，眉眼放松，没有明显惊讶、兴趣或愉悦反应。",
  "body_posture": "面部基本正对镜头，肩膀和脚尖略偏向通道方向，身体重心保留在后脚，呈现随时准备继续走开的姿态。",
  "timeline": {
    "t_0_2": "45岁左右的男性从画面前方经过时放慢脚步，面部转向镜头，双手拿着手机和门禁卡保持在身前。",
    "t_2_5": "他短暂停住，平静地抬眼打量正前方，视线缓慢从上方移到中间位置，身体仍略微朝通道方向偏着。",
    "t_5_8": "他继续沉默观察，眉眼没有明显变化，手指轻轻收紧手机但没有伸手操作，重心开始向离开的方向移动。",
    "t_8_10": "他最后看了一眼正前方，保持平静表情，身体微微转回通道方向，准备继续离开画面。"
  },
  "candidate_actions": [
    "hold",
    "greet",
    "elicit"
  ],
  "outcomes": {
    "hold": {
      "next_aida_stage": "attention",
      "next_bdi": {
        "belief": "设备未施加干扰，继续作为环境一部分被路过者被动注意。他确认设备不会强行推销或打断。",
        "desire": "保持低干扰体验，避免无谓时间浪费；如发现有需求可自由决定是否深入了解。",
        "intention": "停留几秒观察后如无新刺激将平静离开，无被打扰感，设备形象正向提升。"
      },
      "score": 5
    },
    "greet": {
      "next_aida_stage": "attention",
      "next_bdi": {
        "belief": "设备主动唤醒，注意力被强行拉高，但本人无明显兴趣，认为可能是营销行为。",
        "desire": "更倾向快速移开以避免被打扰，对设备小幅反感。",
        "intention": "打算更快结束观察，避免进一步互动。"
      },
      "score": 2
    },
    "elicit": {
      "next_aida_stage": "attention",
      "next_bdi": {
        "belief": "设备直接提问需求，但用户尚未产生兴趣或关注点，反觉突兀。",
        "desire": "减少不必要的互动，优先恢复通路状态。",
        "intention": "认定设备有推销意图，更快决定离开，不考虑操作。"
      },
      "score": 1
    }
  },
  "best_action": "hold",
  "realization": {
    "screen_action": "idle_minimal",
    "voice_style": "silent"
  }
}