{
  "session_id": "piwm_141",
  "persona": "路过办公楼便利区、戴着耳机的年轻男性上班族，被智能零售设备的外观吸引而短暂停下。",
  "persona_visual": "25岁左右的男性，短黑发，戴白色无线耳机，穿浅灰色连帽卫衣和黑色休闲裤，斜挎一个深色通勤包，手里拿着手机。",
  "aida_stage": "attention",
  "bdi": {
    "belief": "他觉得眼前的智能零售设备看起来新颖方便，但还没有明确自己想买什么。",
    "desire": "他想先轻松看看这里可能有什么适合当下顺手购买的东西。",
    "intention": "他倾向于停留几秒继续观察，如果有简单提示或轻松提问，会帮助他明确需求方向。"
  },
  "observable_behavior": "他从路过状态放慢脚步并停在镜头前，戴着耳机，视线在前方上下左右轻轻游移，偶尔低头看一眼手机但没有立即操作。",
  "facial_expression": "表情自然放松，眉眼略带好奇，嘴角平直，没有明显焦虑或强烈购买冲动。",
  "body_posture": "身体正面朝向镜头，站姿较随意，肩膀放松，一只手拿手机停在胸腹前，另一只手自然垂放或轻扶包带。",
  "timeline": {
    "t_0_2": "25岁左右的男性戴着白色无线耳机从画面前方经过，脚步放慢，正面停在镜头前。",
    "t_2_5": "他抬眼看向前方，视线在不同位置轻轻扫动，脸上露出一点被吸引的好奇神情。",
    "t_5_8": "他低头瞥了一眼手里的手机，又抬头继续看，手指轻轻碰着手机边缘，没有做出明确选择动作。",
    "t_8_10": "他保持轻松站姿，眼神仍有些游离，像是在等待一个简单提示来帮助自己想清楚需要什么。"
  },
  "candidate_actions": [
    "hold",
    "elicit",
    "inform"
  ],
  "outcomes": {
    "hold": {
      "next_aida_stage": "attention",
      "next_bdi": {
        "belief": "他依然觉得设备新颖，但缺少进一步了解的契机，需求依然模糊。",
        "desire": "想随便看看，但没有清晰方向，容易失去兴趣继续前行。",
        "intention": "可能继续短暂停留，若无外部刺激则倾向于离开。"
      },
      "score": 2
    },
    "elicit": {
      "next_aida_stage": "interest",
      "next_bdi": {
        "belief": "设备主动简单提问，帮助他意识到可关注的方向（如零食、饮料、应急用品等），逐步聚焦需要什么。",
        "desire": "更愿意思考自己此刻的具体需求，对其中一类商品产生兴趣。",
        "intention": "开始主动在部分商品或品类上做进一步探索，有意愿了解细节或比较选择。"
      },
      "score": 5
    },
    "inform": {
      "next_aida_stage": "attention",
      "next_bdi": {
        "belief": "被动推送信息时，他尚未产生明确需求，接收到的信息未能命中自身关注点，容易视为噪声。",
        "desire": "依旧只是想随便看看，不会因信息展示而改变期望。",
        "intention": "对设备推送内容反应平淡，没有增加探索动力，可能很快结束停留。"
      },
      "score": 1
    }
  },
  "best_action": "elicit",
  "realization": {
    "screen_action": "show_discovery_prompt",
    "voice_style": "soft"
  }
}