{
  "session_id": "piwm_133",
  "persona": "在校园便利区已完成饮品支付、正等待交互收尾的年轻男大学生",
  "persona_visual": "20岁左右的男性，短黑发，穿浅灰色连帽卫衣和深色牛仔裤，背黑色双肩包，双手拿着一部黑色手机",
  "aida_stage": "action",
  "bdi": {
    "belief": "他认为支付已经成功，购买流程基本完成，只需要等待最后确认即可离开。",
    "desire": "他想尽快完成取饮品后的收尾，保持礼貌但不再犹豫。",
    "intention": "他倾向于短暂等待、确认完成后点头致意并离开。"
  },
  "observable_behavior": "他安静站在镜头前，双手握着手机，视线在前方和手机之间自然切换，动作幅度很小，没有明显比较或迟疑。",
  "facial_expression": "表情放松中性，眼神平稳，嘴角略微放松，带有已完成购买后的轻松感。",
  "body_posture": "身体正面朝向镜头，双肩放松，站姿稳定，双手始终在画面内握手机，重心几乎不晃动。",
  "timeline": {
    "t_0_2": "这名穿浅灰色连帽卫衣的年轻男大学生正面站定，双手拿着手机，平静看向前方等待。",
    "t_2_5": "他低头看了一眼手机屏幕，拇指轻轻点按一下，随后把手机保持在胸前偏下的位置。",
    "t_5_8": "他重新抬头看向前方，表情放松，身体微微前倾后恢复站直，像是在确认流程结束。",
    "t_8_10": "他轻轻点头作无声感谢，双手仍握着手机，向后退半步准备离开画面。"
  },
  "target_act": "Greet:close"
}
